<?xml version="1.0" encoding="UTF-8"?>
<LanguageData>
    <Biocoder>生物编码器</Biocoder>
    <enable_weapon_biocode>对所有武器进行生物编码</enable_weapon_biocode>
    <enable_apparel_biocode>对所有服饰进行生物编码</enable_apparel_biocode>
    <restart_needed>重启以生效</restart_needed>
    <Biocoder.BiocoderUsedGainQuality>{1}已成功生物编码为：{0}，并提升品质至{2}。</Biocoder.BiocoderUsedGainQuality>
    <Biocoder.BiocoderUsed>{1}已成功生物编码为：{0}。</Biocoder.BiocoderUsed>
    <Biocoder.BiodecoderUsedLoseQuality>{1}的生物编码：{0}已成功解除，其品质降低至{2}。</Biocoder.BiodecoderUsedLoseQuality>
    <Biocoder.BiodecoderUsed>{1}的生物编码：{0}已成功解除。</Biocoder.BiodecoderUsed>
</LanguageData>